sniparinject/__init__.py
sniparinject/network_sniffer.py
sniparinject/core/__init__.py
sniparinject/core/game.py
sniparinject/core/settings.py
sniparinject/core/text_style.py
sniparinject/core/utility.py
sniparinject-0.0.0.dev7.dist-info/METADATA
sniparinject-0.0.0.dev7.dist-info/WHEEL
sniparinject-0.0.0.dev7.dist-info/top_level.txt
sniparinject-0.0.0.dev7.dist-info/RECORD
