Metadata-Version: 2.1
Name: sniparinject
Version: 0.0.0.dev7
Summary: Intercept and read the network packets to find useful information. Also, inject some data.
Home-page: https://github.com/airvzxf/sniparinject
Author: Israel Roldan
Author-email: israel.alberto.rv@gmail.com
License: GPLv3
Project-URL: Source Code, https://github.com/airvzxf/sniparinject
Project-URL: Bug Tracker, https://github.com/airvzxf/sniparinject/issues
Keywords: network,networking,packet,packets,sniffer,parser,inject,injection,hack,video games,games
Platform: Linux
Platform: Unix
Classifier: Development Status :: 2 - Pre-Alpha
Classifier: Environment :: Console
Classifier: Intended Audience :: Information Technology
Classifier: Intended Audience :: Science/Research
Classifier: Intended Audience :: Telecommunications Industry
Classifier: License :: OSI Approved :: GNU General Public License v3 (GPLv3)
Classifier: Natural Language :: English
Classifier: Operating System :: POSIX :: Linux
Classifier: Operating System :: Unix
Classifier: Programming Language :: Python :: 3
Classifier: Programming Language :: Python :: 3.9
Classifier: Programming Language :: Python :: 3.10
Classifier: Programming Language :: Python :: Implementation :: PyPy
Classifier: Topic :: Games/Entertainment
Classifier: Topic :: Security
Classifier: Topic :: System :: Networking
Classifier: Topic :: System :: Networking :: Monitoring
Requires-Python: >=3.9
Requires-Dist: PyYAML (>=5.4.1)
Requires-Dist: scapy (>=2.4.5)
